cdk_fsx_ontap/__init__.py
cdk_fsx_ontap/py.typed
cdk_fsx_ontap/_jsii/__init__.py
cdk_fsx_ontap/_jsii/cdk-fsx-ontap@1.0.14.jsii.tgz
cdk_fsx_ontap-1.0.14.dist-info/LICENSE
cdk_fsx_ontap-1.0.14.dist-info/METADATA
cdk_fsx_ontap-1.0.14.dist-info/WHEEL
cdk_fsx_ontap-1.0.14.dist-info/top_level.txt
cdk_fsx_ontap-1.0.14.dist-info/RECORD
