Metadata-Version: 2.1
Name: cdk-fsx-ontap
Version: 1.0.14
Summary: CDK construct for Amazon FSx for Netapp ONTAP
Home-page: https://rafalkrol.xyz
Author: Rafal Krol<ameotoko1+github@gmail.com>
License: MIT
Project-URL: Source, https://github.com/rafalkrol-xyz/cdk-fsx-ontap
Classifier: Intended Audience :: Developers
Classifier: Operating System :: OS Independent
Classifier: Programming Language :: JavaScript
Classifier: Programming Language :: Python :: 3 :: Only
Classifier: Programming Language :: Python :: 3.8
Classifier: Programming Language :: Python :: 3.9
Classifier: Programming Language :: Python :: 3.10
Classifier: Programming Language :: Python :: 3.11
Classifier: Typing :: Typed
Classifier: Development Status :: 5 - Production/Stable
Classifier: License :: OSI Approved
Requires-Python: ~=3.8
License-File: LICENSE
Requires-Dist: aws-cdk-lib <3.0.0,>=2.85.0
Requires-Dist: constructs <11.0.0,>=10.0.5
Requires-Dist: jsii <2.0.0,>=1.98.0
Requires-Dist: publication >=0.0.3
Requires-Dist: typeguard ~=2.13.3
